MANIFEST.in
README.md
RELEASE-VERSION
pavement.py
paver-minilib.zip
setup.py
version.py
signal_generator_board_rpc/__init__.py
signal_generator_board_rpc/board.py
signal_generator_board_rpc/protobuf_commands.py
signal_generator_board_rpc/protobuf_custom.py
signal_generator_board_rpc/requests.py
signal_generator_board_rpc/Arduino/signal_generator_board_rpc/Array.h
signal_generator_board_rpc/Arduino/signal_generator_board_rpc/CommandProcessor.h
signal_generator_board_rpc/Arduino/signal_generator_board_rpc/Deserialize.h
signal_generator_board_rpc/Arduino/signal_generator_board_rpc/Node.h
signal_generator_board_rpc/Arduino/signal_generator_board_rpc/NodeCommandProcessor.h
signal_generator_board_rpc/Arduino/signal_generator_board_rpc/SConscript
signal_generator_board_rpc/Arduino/signal_generator_board_rpc/commands_pb.c
signal_generator_board_rpc/Arduino/signal_generator_board_rpc/commands_pb.h
signal_generator_board_rpc/Arduino/signal_generator_board_rpc/commands_pb.o
signal_generator_board_rpc/Arduino/signal_generator_board_rpc/custom_pb.c
signal_generator_board_rpc/Arduino/signal_generator_board_rpc/custom_pb.h
signal_generator_board_rpc/Arduino/signal_generator_board_rpc/custom_pb.o
signal_generator_board_rpc/Arduino/signal_generator_board_rpc/signal_generator_board.cpp
signal_generator_board_rpc/Arduino/signal_generator_board_rpc/signal_generator_board.h
signal_generator_board_rpc/Arduino/signal_generator_board_rpc/signal_generator_board.o
signal_generator_board_rpc/Arduino/signal_generator_board_rpc/signal_generator_board_rpc.ino
signal_generator_board_rpc/firmware/uno/signal_generator_board_rpc.hex
signal_generator_board_rpc/libs/nanopb/pb_decode.o
signal_generator_board_rpc/libs/nanopb/pb_encode.o
signal_generator_board_rpc/protobuf/commands.proto
signal_generator_board_rpc/protobuf/custom.proto
wheeler.signal_generator_board_rpc.egg-info/PKG-INFO
wheeler.signal_generator_board_rpc.egg-info/SOURCES.txt
wheeler.signal_generator_board_rpc.egg-info/dependency_links.txt
wheeler.signal_generator_board_rpc.egg-info/requires.txt
wheeler.signal_generator_board_rpc.egg-info/top_level.txt