Metadata-Version: 1.0
Name: wheeler.signal-generator-board-rpc
Version: 0.3
Summary: Arduino RPC node packaged as Python package.
Home-page: http://github.com/wheeler-microfluidics/signal_generator_board_rpc.git
Author: Christian Fobel
Author-email: christian@fobel.net
License: GPLv2
Platform: UNKNOWN
